{"paths":{"0":["textures/pic_box2_2",3],"1":["textures/pic_box1_2",3],"2":["textures/icon_setup_yingxiao",3],"3":["textures/pic_box11_2",3],"4":["spines/受击特效导出/HIT",4],"5":["textures/zidan1",3],"6":["textures/pic_waikuang_yellow",3],"7":["spines/blood_return/blood_return",3],"8":["textures/pic_shutiao_green",3],"9":["spines/石头碎裂特效/zhuankuaisuilie",3],"10":["textures/pic_box11_3",3],"11":["sounds/se_hit1",2],"12":["textures/pic_box10_3",3],"13":["textures/pic_box2_3",3],"14":["textures/pic_yuanxing",3],"15":["sounds/dao",2],"16":["textures/pic_gezi",3],"17":["textures/pic_waikuang_green",3],"18":["sounds/boss_atk1",2],"19":["textures/btn_blue",3],"20":["textures/btn_yellow",3],"21":["sounds/fail",2],"22":["textures/pic_box3_3",3],"23":["textures/icon_shezhi",3],"24":["textures/pic_box10_4",3],"25":["textures/pic_zhalan_qian",3],"26":["textures/pic_shutiao_yellow",3],"27":["textures/icon_setup_shenying",3],"28":["sounds/win",2],"29":["spines/blood_return/blood_return",4],"30":["textures/pic_box11_4",3],"31":["textures/icon_setup_zhendong",3],"32":["textures/pic_box10_2",3],"33":["sounds/se_recover",2],"34":["sounds/se_hit2",2],"35":["textures/pic_zhalan",3],"36":["textures/pic_kuang_off",3],"37":["textures/pic_caoping",3],"38":["textures/pic_kuang",3],"39":["textures/pic_box1_3",3],"40":["textures/pic_BG1",3],"41":["textures/pic_banzi",3],"42":["textures/pic_box11_5",3],"43":["textures/pic_box1_5",3],"44":["spines/主角动画/player",3],"45":["textures/pic_box3_5",3],"46":["textures/pic_box3_4",3],"47":["spines/受击特效导出/HIT",3],"48":["sounds/se_synthesis",2],"49":["sounds/se_launch",2],"50":["textures/pic_tishi",3],"51":["textures/pic_mubeiBG",3],"52":["spines/recover/buff_7",3],"53":["textures/pic_kuang_on",3],"54":["sounds/click",2],"55":["textures/pic_hengtiao_green",3],"56":["sounds/bgm_knapsack",2],"57":["sounds/se_put",2],"58":["textures/pic_box2_4",3],"59":["textures/pic_box1_4",3],"60":["spines/石头碎裂特效/zhuankuaisuilie",4],"61":["spines/public_vertigo/public_vertigo",3],"62":["sounds/monster_death2",2],"63":["textures/pic_box2_5",3],"64":["textures/pic_box10_5",3],"65":["spines/主角动画/player",4],"66":["spines/recover/buff_7",4],"67":["textures/pic_box3_2",3],"68":["textures/btn_red",3],"69":["spines/public_vertigo/public_vertigo",4],"70":["spines/受击特效导出/HIT",6,1],"71":["textures/pic_zhalan_qian",6,1],"72":["textures/pic_hengtiao_green",6,1],"74":["textures/pic_shutiao_green",6,1],"75":["spines/石头碎裂特效/zhuankuaisuilie",5],"77":["textures/pic_yuanxing",6,1],"79":["spines/recover/buff_7",6,1],"80":["textures/pic_gezi",6,1],"81":["textures/pic_box3_2",6,1],"82":["textures/btn_red",6,1],"85":["spines/主角动画/player",6,1],"86":["spines/石头碎裂特效/zhuankuaisuilie",6,1],"87":["prefabs/equips/MB_Equip_10",1],"89":["textures/pic_box3_5",6,1],"90":["textures/pic_shutiao_yellow",6,1],"91":["animations/enmeyAttack",0],"92":["spines/recover/buff_7",5],"95":["textures/pic_waikuang_green",6,1],"96":["textures/pic_banzi",6,1],"97":["prefabs/enemys/boss3",1],"98":["prefabs/enemys/boss6",1],"99":["prefabs/equips/MB_Equip_8",1],"100":["textures/pic_waikuang_yellow",6,1],"101":["spines/受击特效导出/HIT",5],"102":["textures/pic_tishi",6,1],"103":["textures/btn_blue",6,1],"104":["textures/pic_box11_4",6,1],"105":["prefabs/enemys/boss7",1],"107":["textures/pic_box10_2",6,1],"108":["textures/pic_box1_2",6,1],"109":["textures/pic_box3_3",6,1],"110":["prefabs/equips/MB_Equip_1",1],"112":["prefabs/equips/MB_Equip_9",1],"114":["textures/pic_box2_5",6,1],"116":["textures/pic_box1_4",6,1],"117":["spines/blood_return/blood_return",5],"118":["prefabs/equips/MB_Equip_7",1],"121":["textures/pic_box3_4",6,1],"122":["prefabs/enemys/boss1",1],"123":["textures/pic_box2_2",6,1],"124":["textures/icon_setup_zhendong",6,1],"125":["textures/pic_box2_4",6,1],"126":["textures/icon_setup_yingxiao",6,1],"127":["textures/icon_shezhi",6,1],"128":["prefabs/equips/MB_Equip_2",1],"129":["textures/pic_box11_2",6,1],"130":["popups/MBFailPopup",1],"131":["textures/icon_setup_shenying",6,1],"132":["textures/pic_zhalan",6,1],"135":["prefabs/enemys/boss8",1],"136":["popups/MBWinPopup",1],"139":["textures/pic_box10_4",6,1],"141":["spines/blood_return/blood_return",6,1],"143":["textures/pic_box1_5",6,1],"144":["textures/pic_box11_5",6,1],"149":["textures/pic_box1_3",6,1],"150":["prefabs/enemys/boss2",1],"152":["spines/public_vertigo/public_vertigo",5],"153":["spines/public_vertigo/public_vertigo",6,1],"154":["textures/pic_box2_3",6,1],"156":["prefabs/enemys/zombie_SP4",1],"158":["prefabs/equips/MB_Equip_6",1],"159":["textures/pic_mubeiBG",6,1],"160":["textures/pic_kuang",6,1],"161":["textures/pic_box10_3",6,1],"162":["textures/pic_kuang_on",6,1],"164":["textures/pic_kuang_off",6,1],"166":["textures/pic_box10_5",6,1],"167":["prefabs/equips/MB_Equip_4",1],"168":["prefabs/enemys/boss4",1],"170":["prefabs/equips/MB_Equip_5",1],"171":["prefabs/equips/MB_Equip_11",1],"173":["textures/btn_yellow",6,1],"174":["textures/pic_caoping",6,1],"176":["textures/pic_box11_3",6,1],"177":["prefabs/enemys/boss5",1],"181":["prefabs/enemys/boss9",1],"182":["prefabs/MB_PopHurt",1],"183":["prefabs/equips/MB_Equip_3",1],"185":["spines/主角动画/player",5],"187":["popups/MBSettingPopup",1],"189":["textures/pic_BG1",6,1],"191":["textures/zidan1",6,1]},"types":["cc.AnimationClip","cc.Prefab","cc.AudioClip","cc.Texture2D","cc.Asset","sp.SkeletonData","cc.SpriteFrame"],"uuids":["04kzVmkklJGL5IQh5q6rXM","06xrtX+m9HhrmVP8jAa/z0","069IYCIQVAU7zx709YC7HX","0a/mqrnE5J3KizKMsq/vKI","10daemKOhARY4FB5MypKJJ","101hO96wpNqacpJTCbKOGr","16NclmN51CXbjp33epxX0s","16vzvAT1hAp7CkcX/xlapR","185KgUrHZEBLWlydezG8Cx","19FIlkgIBCnZS7Gtq9oV9d","1cOhZWnitIsKx/Wlzt8ptB","2fxawF1YdAc5Z5xhj2clYv","30V8RHIclFgZZidfP7LhtX","389XOFVWpBNLmHiO8kWNaY","3boxCj00dITpNBbSs5vJq9","3dZ5UfQuVH44sMLZXPLyic","3eD8q0fk1KSrpR435ry+in","41Jq/k0h1E2YzaqsLCv1qM","42FqYFnC9FRK5VUB5EJ6/Q","49ZC+MdKlNaIJJJP4GMmKt","4eUd6S6ilPLJRz9QSnDWTm","4evSDGM7hNHJunNIWHGJX/","55tRcHRhpOG4TTGDQqDtmE","5ev/5mb9JCB6XN/veudqOY","61ssMetpNKup1rUlDXtX8x","61zCjn8mlEf6jqSekhKui6","63RwK/GuhA0bs2nEsPJ/s9","64cmhGoyFCQYyAcNDnT2lS","64ese+mnBJlIcQL8xY/MrD","67vm4wWnFBe5niywVbZzGi","68eqXTcZVODYcHvStPdd6B","7cuJg2RD1CCoJ1QF5UVm+U","7d/REsS8JKHop5lCdHKPkM","7eLZmqXWpGH5d1NX/7hn1e","8bVYqP/x1MfbGfcffW0G6X","8fUitKDb9MfbYtO3QKIG6g","95+/loIaNKKIfYvhX3L2dk","96MklrZJdNjb+SsBz2nxR0","97JauhvF9H36JNUrf0frHD","9bcVHBqQhDQbZaSnmSpL9b","9ci4vYf6dAN6p8CjjV/FGL","a43m7v3l1FFaQAQ3i9Bavk","a6SY53hlRBeZ3Ee7npDr1y","a7N9EJ7VFFHpafQbBBcoYG","b0/Hx8USlH6Lu9VW/D4QhC","b6xHzPsyFOSLdmSOPe3uOY","beyI3Z5MVDn4iBLyw5J9qH","c1FpUPj3lHMqNyjE24RW4K","c3uaFL0K9N/ZBlP34kwiZS","c4V+13KFpB2JYA5U5aMC+L","c5WKoUBTpKbrvFvqfCgEWl","caoFpc3MhHrbm+CUbXlDXX","cc9iwpKB1JzLEEw6yUPJvO","ceMrVOLZxB/KcLnURlJUO4","cefu7VCUFHNrOBdrn+u5Cf","d5p099PHFLeLzW3D1LnUrj","daWh7b5RlDrJfYlTo18I2U","ddDWqj8INP4IpzSGzHKgZQ","e0rl9q8I9D8pLX32WgIYRP","e2G8wdvNtN8L7+8SzReBXI","e4rd5dw3pJlKUtynj7uz8K","e6Bm6G+bBGOpEI218RTd13","eah3uikjFJ35PxfIms8AbL","ecmfxYulVNGosrk77u2LPL","efRSNYvMpIB7zUOK4KEAtp","ef2AZlFw5BxpQ3km8zEvkD","f5cVvGHTxOH4TwLYKwa2+N","f62s5TSetAtpaldJ7ejp3T","fbCjorUZNPkZloBHJOEcDW","ffrNBgBcFO4bR91TtpEwEy","01F5WLn9lOVqhRoMz+1CKu","01T0AdERhFFYnB7pZ/04AX","01gom6QPJNWYYj7H4iK9Id","05e5m2C3NBC4EFzWzb0iov","06IlmqfAJCxYfM/tMDHJ0m","09rr57S2NN7K/8EY3oSyoL","1201bb519","14aBa0xbFAkKt4UxCsdHsz","17db252ea","1crCaRdZRGoaLqrb6udVPo","1dEuIemNhEaJUq2lGMuxdX","1dz7wwm65IQ6tAjmvGZdlg","1fJqoXMUFFS4/dL9UZq0g+","1funuz8FNG/ZGuvd2sS1qE","21FwfzCp1OTbUs7B2zqA+O","21OnhNNBdKj5L8OeVS654F","24PWZa+dJDGILEelbbYeiG","27hD0V+OpIArSxjU3ZlSO3","2aFky7cORMaL1qL5kJDY5q","2ask4csvVNRKCEB/abvG/u","2eCGSr+JFOe49+fwg0Iojb","2fy/EN7zdDW5dgABSiQoE8","3fpZRbgnlD4Zs1Bt5mqF2x","44XphLR4BNDYQmo8KXlzyI","44j59ElHFCH5bbKvHKMSeg","44lCAQSaBMw7myJ94Uvkev","44uxGigChE4IsUmmia3pvg","47Jf+JhhdORJsy5znoahdL","4ab2XkG+RLcpF41a9mBmqG","4cHpgLUstGopSWIhw7mjU+","4dfyUS3SVMdqoNRJ4dsapY","517cIBx9VCpYuz9vlLDnhE","52q/s3fLVKZam2hogbWpSM","52/NcZ94JI544zdOhYkLBW","54C2v7SiFIy68PSeMcyUUV","55EzEaBDxMt4CuzMDriUIA","56DHOAsJ5Hl7/MdYxwwus4","56wF8wDt9OELe+MhZY9t4V","5c6HJt22BCnImtMf8aOdg4","5ds9uuhMRBeaIdq5JPbVx8","5eWuy1qjJIbL4cjFCa6CT5","60A6K9swVP5Z8s70MUcgai","63vyqXJj1IYIMWPEd+En4g","639CKD60pJ9a8le+RuflWz","68zXlCm7BMtKbNFXFpZw8z","69EqOzRupIJKCJvUm953DV","6aBi8QypBBAapgvaNUOKMr","6bdA+wUhREbbs6nXmhTuVL","6ckGSd/I5LMp8i4sCD+g2C","6eQLaPcTBFcqgHBfwWUv8H","72v7dklHNHFKy2HH09MRNj","73VvW5w7NIz7ro4MVLosCV","738/4I2xlPw7CAC76j5njX","76AZGjqrlExY4kqb8WyFI7","77gYiB2c5D36CfY9G2ApKp","79uvh01hZHtqbvrO3i4bR8","7bQq1k6cpNKbAZ8SZnV1MJ","7cq0HVmzBBBbSPiVO1B7ZB","7dIWRbTsBDIZz0X+gPs70I","7fSRcLRYdDE5xv6CY+Fd1y","7fo8s0e5BOhpY82lL4Ig9h","82ylJ+I5VDW7aMw5nfgdXk","834LbdPENLEoszxs50EdtR","85a12ZXnRNI4j/EvAwAIRg","8d3dOwp8JMxKAw1PIrQcqP","91xFvvrkRLVZyyPHqA2v1y","93Z6mmHQdL/6I/rWt1Soq1","94RYW9Q/FDn4iUP3skXIBU","94qpPRiutMMqTWFzkz3XOn","9aoXTOqGpFj7sSsayOmYyf","9b74MRTd9LWLtIUMDPhjzq","9dqYPFxRRAir0DNUF93Xm6","a1echq6o1NJ5/Iqo9CD9jF","a2XQQ+3lFPeojpzH2YGwh3","a3VF7FWPJN4KMYG2eYahnJ","a5Vk1/UBJM+r79VVWqLSVx","a6CUNHhmJLILJaXQ4LAAuK","a8hR/Jl0ZGj4ZBwPUb5rj9","abVWGD7aZOJKn/hagqc0HG","afh2MYJNZDtI5F1kWqFH15","b0QA+fdvJJ3Y34a0q/33y9","b0hHcJKy1Map34c3LTtP6w","b4c68Ihm9KzJHyEYeJBtga","c35L6rKbtBCoxUuM/0q6Wh","c4r0MpRQNFNLMxHZyJzzrR","c4vF/SAZxFFI7o2AG9SVv0","c5S0HJ5UpHd4wx/5Lz9mSB","c68a8LT3xPkJByo5uFHbrA","cb25ak33hCa72z5JY9rkZU","ccSDncPGBL/K7pipJZeZqx","cciiiIiJxG2KSqBiZZjlTy","cclSmrKNRAr7quMTlJ/keS","cd1gXFSrBBaIxdvvnIcmdQ","cewgvl/v5NPbN9ZiWECe85","cfy6b7aolBcYoa1ExoMy6n","d4iq89AvZBlLPG/FEL+jAO","dbEgt4DfVCtJ1RF1gv0BUV","dcwffFcKZBFZdfiv4qEsvf","ddUDorbU5D1IBAaGjdDSLU","dezYhqvWdCM5sXpyt4cv+j","e0tcMKRnlFxovU4GOs4bGs","e2QLiiUZ1J/qTXC6pnnEIO","e2dj0C9RpJK5vfe3v3eWQC","e32v5daOxMf4AhcS3++ePj","e4Gqjqq6dCSqMd44C7Joo7","e5b5EO1I5I4Y32YIof4+KF","e9DYeBF2JK96y2vb95/Kuz","eaa1FYtcFGn756DmyciwpF","ed0hW5J5ZKBar1gflskoHO","f03JMI0QBFC7Xs7q8JYO1a","f1dxmX4/5EE51T8IMKAeDn","f10MWDl9JEiYooCpdH04wa","f2+Xtzq2ZNurYioEpPG8+G","f3KO3RXUxMtpcLx6vEpOpM","f36g/4XyxHR4LCKsGsomRB","f5GhPr/FlIg7BcMVZeVWtF","f5W1PKVR9B4bNWKt0T9kiC","f6VlxoAo5O5IUkg1K7itia","fahmml+s5NI44kVOVvk5sC","favaIxRWBELYuITaTysmww","fa8EK6mhRCs5ZWic54LQgI","febEuK0sRESKxxIvMgyaXR","03TgHlQLtCNKcPeIu4Iqs0","07o00hz2JIboizbc5wT5WX","08K9AccmxGvYnzlfjh3qUD","09aodFfQVCWI9t6JcznKYw","0aTfksQu1JIrEy74VZEH9+","0cwej++kNCGb41WcSrJgrI","12E9JGXO9NBrbhOThMMQ8w","151gvnSj5GHoqXrGhe49Zl","19Jx1LSN5CxYwi0g38PQPQ","22tk/LRt1C+r4UyvSznM/4","24uuhLw39KP5wI6dBBN11E","28DFHe5ZtPeJtIIMqV9PLL","29+tg7sSlJh5/C+iB/yY1h","2eFnlUEEJHMIo04nYC3S0s","377flPILtEjohDmyA6rxlv","38Nc2Sp8dGG4HB0Pr2h3Lg","38Slwj7/xNl4d7IH2BzFpd","38+T6lXV5IzLaAwBqagkhl","3dDgZqu0hNIbwSxNyN18Tl","3fAf7Hxe1MS7ZTiPS7uGrP","40JtAYLDhLUJIr62Qtiot7","46RoDVzc5BaLopzSwJLAGd","4atKlpUGtP7LI4JXsXUYYV","505g3YHYdKZJT8eyrRpVox","52Cpiu6wxF14wXAuKy01kr","542nJvF1hLh4QHvVGy2TAT","55RS8KTlxHV75j1zB93DKa","5d1wMzcmVOJpYGOWmshbh5","5ezWySeApLV4yCwSh5NNo+","5fi1ooANxC6pdMx03tFbUB","61Zo3cztNDtbY0v9z0wy7T","64cHTjoU1PGbeaWhmNQrTB","66yFQ749FNJ5xP13AvEW+m","67jRpPktRBMIv4BrmPEGYu","6ddy20fNFJh4e1qRUvFycY","6fGf5nr0RC96ZZkrQ3sTc4","769cpa7KJKn7ehKESj/zpi","79XsTQcTNHMJlmYp/AKOuF","7a/QZLET9IDreTiBfRn2PD","7eBAgLiuhAPLbMJblmqxVN","7fcZtBKmhBKIpunnPHiHL0","7frdevfcFBppcVGc2+w57B","81iRrZZX9ImoLE/CLyW1aA","813nCc1IBOcpkkTACUBj46","81+6z+gH9MGLdUNSTZb6xY","8eucXoWuZC05pK+ruRyV4Y","90Mt5C8IpLfZBjTlGdC4q4","91O9TaYqtBt4Jal/Trxms+","93VbsdsgVEnJrghlrbfZ15","94XxoMOiVMSoYDIjg6wOrj","9d7ja2TldNP6kKfx/35zI3","a2MjXRFdtLlYQ5ouAFv/+R","a4oGLLDEZCNZwUdtAijfEe","b1P+LDZANDnr5xGJATSEIM","baWQ63cbpALZMQlXf5RWY8","c2YaM9DDtPRoYIQe0tYVb9","c2gfiKf7dMppqG6e7FaUN6","ceGlAvxQ1DuqfNCsRQFq1N","ce14e9OR9AGL0DKnBBLo5C","ce8ooDRMFKS6TsV5hmvnRR","d0dW67VntN6ZkMkTd9KFlS","d3TI54Dg9Pyo7jMs1kbRsH","d3g7eWvepLO6YFj6RuMO40","d4RASGb5FFqJ4XYfwvyw2s","d5Rv6PaQFOGZ8lvTMsQxWF","d7mb5xj8xDlYvCLqFRmU1u","d8eiG1tF1OQ6g1RYkNJMt4","d89zKcqIRDY6k/L1Fbgt0X","d9nT9vQVhNT70iWuozNygz","dbpabiINFGaJqECyKbMsgR","dcJwLp67xJo561AOuPEJuv","dc8DhhYNdDmZ++/VpLESUQ","e2LC0aMgtCroJRNAHOYyuf","e8bCYIJJRFL5m3T9M4HEIH","ebciCTeXNPNJ/YbFD6vGbB","ecSzh6CRBBXpZbfs8NFC0n","ecpdLyjvZBwrvm+cedCcQy","ec/oMqtY5BgZmpTEYdSC/T","eeqJzpp4tKvYxHFXbXecG+","f0Oc2eKJ5K3LjYKLYanJWI","f1OUHEteFH4Y70IqfyOo5w","f2UhA8svtET6kdRZX5KFDA","f5FEAowDVEw7P2qK8syb8B","f926SQ6VRGnKdJhxj4738g","faX8FuaI9MeYcPgZipFVQy","fbwpvKVRhMArOH76pXxYL7","fcEaRc9edMk7F+nF5XAQ4Z","feR4P5swJE67Yzh1M7tkK1","ffDpHHVcZAhqOfy25Fe4w7"],"scenes":{"db://assets/res_MB/mb.fire":93},"redirect":[230,0,243,1,260,2,268,0],"deps":["internal","main","resources"],"packs":{"01b4ab8ed":[199,202,249,262],"01b5cd300":[156,261],"02000cd6c":[128,264],"02b1d3d3f":[105,231],"03ba8b77b":[170,271],"04119ce66":[193,198,130,240],"0523e95cd":[194,208,221,222,223,224,229,235,238,241,272,273,187,279],"05f22a51c":[0,73,1,2,3,5,76,6,7,78,8,9,10,83,84,88,12,13,14,16,17,94,19,20,22,23,111,24,25,26,113,27,30,115,119,120,31,32,133,134,35,137,138,36,37,38,39,140,40,142,41,145,146,42,43,147,148,151,44,45,46,47,155,50,157,51,52,53,163,165,55,169,58,59,172,175,61,63,178,64,179,180,184,186,67,188,190,68],"062eb555a":[112,239],"063883716":[212,158],"07763398f":[203,99],"088b59ce4":[135,263],"0961da52d":[200,118],"09e64ffe0":[214,150],"0a668b75f":[216,255,275,276],"0aedf078e":[98,227],"0b224eb69":[201,110],"0c2a12754":[122,234],"0c4180e67":[177,269],"0c9ca2bab":[211,244,247,257],"0ca0e580d":[204,205,217,236,136,246,259,267,274],"0ca7fe06d":[97,270],"0d0a87772":[87,245],"0d1195950":[219,168],"0dd6030f7":[213,218,254,167,265,278],"0e9f3d25f":[206,183],"0ecb6d2ed":[192,197,207,209,210,93,215,220,225,226,233,242,248,250,251,252,258,266,277],"0f20e91a4":[195,196,232,253],"0f738969a":[228,181],"0fd520eb3":[256,171]},"name":"res_MB","importBase":"import","nativeBase":"native","debug":false,"isZip":false,"encrypted":false,"versions":{"import":[70,"7022a",71,"b5983",72,"e77d3","01b4ab8ed","d18f6","01b5cd300","91787","02000cd6c","b3e11","02b1d3d3f","dcb25","03ba8b77b","cc597","04119ce66","be9f7","0523e95cd","8f4bd","05f22a51c","6d967",74,"8307d","062eb555a","90df5","063883716","d6692","07763398f","f04ff","088b59ce4","72378","0961da52d","e8a83",75,"119b4","09e64ffe0","5e147","0a668b75f","9a486","0aedf078e","c6538","0b224eb69","7aff1","0c2a12754","35566","0c4180e67","f52c9","0c9ca2bab","41f5a","0ca0e580d","9a588","0ca7fe06d","9d31d","0d0a87772","8d147","0d1195950","e1a8d","0dd6030f7","edd09","0e9f3d25f","78072","0ecb6d2ed","19c40","0f20e91a4","326f6","0f738969a","347f4","0fd520eb3","7c490",4,"f007b",77,"f01e5",79,"adc85",80,"beb80",81,"6a2bd",82,"bf318",85,"cdca0",86,"6e817",89,"6b304",90,"c9976",11,"b1c9d",91,"d8110",15,"16c63",92,"4b213",18,"30b87",95,"1d5e1",96,"e3eef",100,"a6875",21,"72c53",101,"ff8eb",102,"8b45c",103,"0511e",104,"ed523",106,"f1b86",107,"0d9ef",108,"02aea",109,"c11ab",28,"2a5c7",29,"861b8",114,"93496",116,"1c817",117,"9db66",121,"d2189",123,"8b349",124,"2aa17",125,"88bea",126,"dcd25",127,"951f8",33,"1fb76",129,"2c4af",131,"c74e3",132,"00c05",34,"a36fc",237,"79950",139,"a7036",141,"d1a8e",143,"02d5b",144,"13ae3",149,"04708",152,"8ec22",48,"b370f",153,"9aabb",49,"ae0cc",154,"51001",159,"0ff4b",160,"e34ac",161,"50bbd",162,"1e1ac",54,"ebd59",164,"fdce9",56,"cd3d1",166,"2b55e",57,"b3e98",173,"878ce",174,"22d0b",60,"c5bd9",176,"ac488",62,"16862",65,"2dcfd",182,"b902c",185,"9aeac",66,"9b9e5",189,"61e91",191,"528f4",280,"68f7d",69,"6f657"],"native":[0,"d4f8f",73,"58ea6",1,"a4c07",2,"d7e07",3,"ba867",4,"d4465",5,"fbff3",76,"576ae",6,"8ef32",7,"03b3d",78,"4059c",8,"33794",9,"ea1d1",10,"b422e",83,"155f7",84,"9a9fa",88,"1918f",11,"9a0e9",12,"80d07",13,"8ea1a",14,"48c49",15,"0e90d",16,"ca28d",17,"21ccc",18,"58d07",94,"a7622",19,"a663a",20,"ce6cd",21,"74e68",22,"37ac1",106,"f12b2",23,"b1853",111,"3f5e7",24,"fcbb2",25,"fc4cb",26,"fc665",113,"232ea",27,"52929",28,"56426",29,"e0324",30,"bc131",115,"32241",119,"a5d08",120,"4dd9b",31,"d56de",32,"0c0da",33,"1622d",133,"42c54",34,"40182",134,"2c04f",35,"07dc1",137,"06cfe",138,"66631",36,"f1f7e",37,"43043",38,"d7acb",39,"84da7",140,"a2909",40,"c59c8",142,"05079",41,"b4980",145,"e9025",146,"de947",42,"3a0c4",43,"b8109",147,"87e55",148,"6d310",151,"c4824",44,"c94fa",45,"00e81",46,"91b0d",47,"67c8a",48,"e2880",49,"2da9c",155,"3dc30",50,"82d1b",157,"81dc7",51,"f3a80",52,"2f3f1",53,"f83a3",54,"3da86",163,"d9410",165,"24d02",55,"5a163",56,"7dd73",57,"23bd1",169,"1ed15",58,"5b5b8",59,"35a6b",172,"dad86",60,"775d0",175,"02332",61,"42402",62,"1e2dd",63,"7062b",178,"17df6",64,"e9fce",65,"85bfc",179,"b3fff",180,"0e02e",184,"4a5d0",186,"ccbb4",66,"5a404",67,"528cb",188,"2776f",190,"ca7ac",68,"0b25f",69,"e059c"]}}